{"type": "player", "href": "/ayoze-perez/profil/spieler/246968", "parent": {"type": "club", "href": "/leicester-city/startseite/verein/1003/saison_id/2020", "seasoned_href": "https://www.transfermarkt.co.uk/leicester-city/startseite/verein/1003/saison_id/2020/saison_id/2021"}, "name_in_home_country": "Ayoze P\u00e9rez Guti\u00e9rrez", "date_of_birth": "Jul 29, 1993", "place_of_birth": {"country": "Spain", "city": "Santa Cruz de Tenerife\u00a0\u00a0"}, "age": "28", "height": "1,78 m", "citizienship": "Spain", "position": "Second Striker", "player_agent": {"href": "/interlex-sport/beraterfirma/berater/5491", "name": "InterLex Sport"}, "current_club": {"href": "/leicester-city/startseite/verein/1003"}, "foot": "right", "joined": "Jul 4, 2019", "contract_expires": "Jun 30, 2023", "day_of_last_contract_extension": null, "outfitter": "adidas", "social_media": ["http://twitter.com/AyozePG", "http://www.instagram.com/ayozepg/"]}
{"type": "player", "href": "/luke-thomas/profil/spieler/505194", "parent": {"type": "club", "href": "/leicester-city/startseite/verein/1003/saison_id/2020", "seasoned_href": "https://www.transfermarkt.co.uk/leicester-city/startseite/verein/1003/saison_id/2020/saison_id/2021"}, "name_in_home_country": "Luke Jonathan Thomas", "date_of_birth": "Jun 10, 2001", "place_of_birth": {"country": "England", "city": "Syston"}, "age": "20", "height": "1,81 m", "citizienship": "England", "position": "Left-Back", "player_agent": {"href": "/wasserman/beraterfirma/berater/440", "name": "Wasserman"}, "current_club": {"href": "/leicester-city/startseite/verein/1003"}, "foot": "left", "joined": "Jul 1, 2020", "contract_expires": "Jun 30, 2024", "day_of_last_contract_extension": "Aug 25, 2020", "outfitter": null, "social_media": ["http://www.instagram.com/lukethomas_3/"]}
{"type": "player", "href": "/jannik-vestergaard/profil/spieler/99331", "parent": {"type": "club", "href": "/leicester-city/startseite/verein/1003/saison_id/2020", "seasoned_href": "https://www.transfermarkt.co.uk/leicester-city/startseite/verein/1003/saison_id/2020/saison_id/2021"}, "name_in_home_country": null, "date_of_birth": "Aug 3, 1992", "place_of_birth": {"country": "Denmark", "city": "Hvidovre"}, "age": "29", "height": "1,99 m", "citizienship": "Denmark", "position": "Centre-Back", "player_agent": {"href": "/international-sports-management-ismg-/beraterfirma/berater/563", "name": "ISMG International"}, "current_club": {"href": "/leicester-city/startseite/verein/1003"}, "foot": "both", "joined": "Aug 13, 2021", "contract_expires": "Jun 30, 2024", "day_of_last_contract_extension": null, "outfitter": "adidas", "social_media": ["http://twitter.com/JVestergaard7", "http://www.instagram.com/jannikvestergaard/"]}
{"type": "player", "href": "/wesley-fofana/profil/spieler/475411", "parent": {"type": "club", "href": "/leicester-city/startseite/verein/1003/saison_id/2020", "seasoned_href": "https://www.transfermarkt.co.uk/leicester-city/startseite/verein/1003/saison_id/2020/saison_id/2021"}, "name_in_home_country": null, "date_of_birth": "Dec 17, 2000", "place_of_birth": {"country": "France", "city": "Marseille"}, "age": "20", "height": "1,90 m", "citizienship": "France", "position": "Centre-Back", "player_agent": {"href": "/ttma/beraterfirma/berater/7736", "name": "TTMA"}, "current_club": {"href": "/leicester-city/startseite/verein/1003"}, "foot": "right", "joined": "Oct 2, 2020", "contract_expires": "Jun 30, 2025", "day_of_last_contract_extension": null, "outfitter": "adidas", "social_media": ["http://www.instagram.com/lawestt_/"]}
{"type": "player", "href": "/kasper-schmeichel/profil/spieler/16911", "parent": {"type": "club", "href": "/leicester-city/startseite/verein/1003/saison_id/2020", "seasoned_href": "https://www.transfermarkt.co.uk/leicester-city/startseite/verein/1003/saison_id/2020/saison_id/2021"}, "name_in_home_country": "Kasper Peter Schmeichel", "date_of_birth": "Nov 5, 1986", "place_of_birth": {"country": "Denmark", "city": "Kopenhagen"}, "age": "34", "height": "1,89 m", "citizienship": "Denmark", "position": "Goalkeeper", "player_agent": {"href": "/p-amp-p-sport-management-s-a-m-/beraterfirma/berater/206", "name": "P&P Sport Management S.A.M."}, "current_club": {"href": "/leicester-city/startseite/verein/1003"}, "foot": "right", "joined": "Jul 1, 2011", "contract_expires": "Jun 30, 2023", "day_of_last_contract_extension": "Aug 31, 2018", "outfitter": "New Balance", "social_media": ["http://twitter.com/kschmeichel1", "http://www.facebook.com/kasperschmeichelofficial/", "http://www.instagram.com/kasperschmeichel/"]}
{"type": "player", "href": "/kelechi-iheanacho/profil/spieler/295330", "parent": {"type": "club", "href": "/leicester-city/startseite/verein/1003/saison_id/2020", "seasoned_href": "https://www.transfermarkt.co.uk/leicester-city/startseite/verein/1003/saison_id/2020/saison_id/2021"}, "name_in_home_country": "Kelechi Promise Iheanacho", "date_of_birth": "Oct 3, 1996", "place_of_birth": {"country": "Nigeria", "city": "Imo"}, "age": "24", "height": "1,85 m", "citizienship": "Nigeria", "position": "Centre-Forward", "player_agent": {"href": "/icm-stellar-sports/beraterfirma/berater/190", "name": "ICM Stellar Sports"}, "current_club": {"href": "/leicester-city/startseite/verein/1003"}, "foot": "left", "joined": "Aug 3, 2017", "contract_expires": "Jun 30, 2024", "day_of_last_contract_extension": "Apr 3, 2021", "outfitter": "Nike", "social_media": ["http://twitter.com/67kelechi", "http://www.instagram.com/kelechi72"]}
{"type": "player", "href": "/hamza-choudhury/profil/spieler/341501", "parent": {"type": "club", "href": "/leicester-city/startseite/verein/1003/saison_id/2020", "seasoned_href": "https://www.transfermarkt.co.uk/leicester-city/startseite/verein/1003/saison_id/2020/saison_id/2021"}, "name_in_home_country": "Hamza Dewan Choudhury", "date_of_birth": "Oct 1, 1997", "place_of_birth": {"country": "England", "city": "Loughborough"}, "age": "23", "height": "1,78 m", "citizienship": "England", "position": "Central Midfield", "player_agent": {"href": "/wasserman/beraterfirma/berater/440", "name": "Wasserman"}, "current_club": {"href": "/leicester-city/startseite/verein/1003"}, "foot": "right", "joined": "Jan 1, 2018", "contract_expires": "Jun 30, 2023", "day_of_last_contract_extension": "Aug 30, 2019", "outfitter": null, "social_media": ["http://www.instagram.com/hamzachoudhury11/"]}
{"type": "player", "href": "/boubakary-soumare/profil/spieler/344605", "parent": {"type": "club", "href": "/leicester-city/startseite/verein/1003/saison_id/2020", "seasoned_href": "https://www.transfermarkt.co.uk/leicester-city/startseite/verein/1003/saison_id/2020/saison_id/2021"}, "name_in_home_country": null, "date_of_birth": "Feb 27, 1999", "place_of_birth": {"country": "France", "city": "Noisy-le-Sec"}, "age": "22", "height": "1,88 m", "citizienship": "France", "position": "Defensive Midfield", "player_agent": {"href": "/sport-avenir-management-international/beraterfirma/berater/2496", "name": "Sport Avenir Management International"}, "current_club": {"href": "/leicester-city/startseite/verein/1003"}, "foot": "right", "joined": "Jul 2, 2021", "contract_expires": "Jun 30, 2026", "day_of_last_contract_extension": null, "outfitter": "adidas"}
{"type": "player", "href": "/filip-benkovic/profil/spieler/293168", "parent": {"type": "club", "href": "/leicester-city/startseite/verein/1003/saison_id/2020", "seasoned_href": "https://www.transfermarkt.co.uk/leicester-city/startseite/verein/1003/saison_id/2020/saison_id/2021"}, "name_in_home_country": "Filip Benkovi\u0107", "date_of_birth": "Jul 13, 1997", "place_of_birth": {"country": "Croatia", "city": "Zagreb"}, "age": "24", "height": "1,94 m", "citizienship": "Croatia", "position": "Centre-Back", "player_agent": {"href": "/futureball/beraterfirma/berater/7562", "name": "FutureBall"}, "current_club": {"href": "/leicester-city/startseite/verein/1003"}, "foot": "right", "joined": "Aug 9, 2018", "contract_expires": "Jun 30, 2023", "day_of_last_contract_extension": null, "outfitter": null, "social_media": ["http://www.instagram.com/filip.benkovic/"]}
{"type": "player", "href": "/francisco-trincao/profil/spieler/412669", "parent": {"type": "club", "href": "/wolverhampton-wanderers/startseite/verein/543/saison_id/2020", "seasoned_href": "https://www.transfermarkt.co.uk/wolverhampton-wanderers/startseite/verein/543/saison_id/2020/saison_id/2021"}, "name_in_home_country": "Francisco Ant\u00f3nio Machado Mota Castro Trinc\u00e3o", "date_of_birth": "Dec 29, 1999", "place_of_birth": {"country": "Portugal", "city": "Viana do Castelo"}, "age": "21", "height": "1,84 m", "citizienship": "Portugal", "position": "Right Winger", "player_agent": {"href": "/gestifute/beraterfirma/berater/413", "name": "Gestifute"}, "current_club": {"href": "/wolverhampton-wanderers/startseite/verein/543"}, "foot": "left", "joined": "Jul 4, 2021", "contract_expires": "Jun 30, 2022", "day_of_last_contract_extension": null, "outfitter": "Nike", "social_media": ["http://www.facebook.com/FranciscoTrincao77/", "http://www.instagram.com/trincao/"]}
{"type": "player", "href": "/joel-ward/profil/spieler/92572", "parent": {"type": "club", "href": "/crystal-palace/startseite/verein/873/saison_id/2020", "seasoned_href": "https://www.transfermarkt.co.uk/crystal-palace/startseite/verein/873/saison_id/2020/saison_id/2021"}, "name_in_home_country": "Joel Edward Philip Ward", "date_of_birth": "Oct 29, 1989", "place_of_birth": {"country": "England", "city": "Emsworth"}, "age": "31", "height": "1,86 m", "citizienship": "England", "position": "Right-Back", "player_agent": {"href": "/avid-sports-amp-entertainment-group/beraterfirma/berater/4959", "name": "Avid Sports Group"}, "current_club": {"href": "/crystal-palace/startseite/verein/873"}, "foot": "right", "joined": "Jul 1, 2012", "contract_expires": "Jun 30, 2023", "day_of_last_contract_extension": "Jul 15, 2021", "outfitter": null, "social_media": ["http://twitter.com/JoelWard2", "http://www.instagram.com/joelward2/"]}
{"type": "player", "href": "/jairo-riedewald/profil/spieler/241481", "parent": {"type": "club", "href": "/crystal-palace/startseite/verein/873/saison_id/2020", "seasoned_href": "https://www.transfermarkt.co.uk/crystal-palace/startseite/verein/873/saison_id/2020/saison_id/2021"}, "name_in_home_country": "Ja\u00efro Jocquim Riedewald", "date_of_birth": "Sep 9, 1996", "place_of_birth": {"country": "Netherlands", "city": "Haarlem"}, "age": "25", "height": "1,82 m", "citizienship": "Netherlands", "position": "Defensive Midfield", "player_agent": {"href": "/seg-sports-entertainment-group/beraterfirma/berater/586", "name": "SEG"}, "current_club": {"href": "/crystal-palace/startseite/verein/873"}, "foot": "left", "joined": "Jul 24, 2017", "contract_expires": "Jun 30, 2024", "day_of_last_contract_extension": "Feb 3, 2021", "outfitter": "adidas", "social_media": ["http://www.instagram.com/jriedewald/"]}
{"type": "player", "href": "/remi-matthews/profil/spieler/196722", "parent": {"type": "club", "href": "/crystal-palace/startseite/verein/873/saison_id/2020", "seasoned_href": "https://www.transfermarkt.co.uk/crystal-palace/startseite/verein/873/saison_id/2020/saison_id/2021"}, "name_in_home_country": "Remi Luke Matthews", "date_of_birth": "Feb 10, 1994", "place_of_birth": {"country": "England", "city": "Gorleston"}, "age": "27", "height": "1,92 m", "citizienship": "England", "position": "Goalkeeper", "player_agent": {"href": "/footfeel-amp-echo-sports/beraterfirma/berater/4477", "name": "Footfeel & Echo Sports"}, "current_club": {"href": "/crystal-palace/startseite/verein/873"}, "foot": "right", "joined": "Jul 12, 2021", "contract_expires": "Jun 30, 2023", "day_of_last_contract_extension": null, "outfitter": null, "social_media": ["http://twitter.com/Remi_matthews", "http://www.instagram.com/remimatthews/"]}
{"type": "player", "href": "/jaroslaw-jach/profil/spieler/327755", "parent": {"type": "club", "href": "/crystal-palace/startseite/verein/873/saison_id/2020", "seasoned_href": "https://www.transfermarkt.co.uk/crystal-palace/startseite/verein/873/saison_id/2020/saison_id/2021"}, "name_in_home_country": "Jaros\u0142aw Przemys\u0142aw Jach", "date_of_birth": "Feb 17, 1994", "place_of_birth": {"country": "Poland", "city": "Bielawa"}, "age": "27", "height": "1,92 m", "citizienship": "Poland", "position": "Centre-Back", "player_agent": {"href": "/pawel-staniszewski/beraterfirma/berater/1489", "name": "Pawel Staniszewski"}, "current_club": {"href": "/crystal-palace/startseite/verein/873"}, "foot": "left", "joined": "Jan 23, 2018", "contract_expires": "Jun 30, 2022", "day_of_last_contract_extension": null, "outfitter": null}
{"type": "player", "href": "/cheikhou-kouyate/profil/spieler/66934", "parent": {"type": "club", "href": "/crystal-palace/startseite/verein/873/saison_id/2020", "seasoned_href": "https://www.transfermarkt.co.uk/crystal-palace/startseite/verein/873/saison_id/2020/saison_id/2021"}, "name_in_home_country": null, "date_of_birth": "Dec 21, 1989", "place_of_birth": {"country": "Senegal", "city": "Dakar"}, "age": "31", "height": "1,89 m", "citizienship": "Senegal", "position": "Defensive Midfield", "player_agent": {"href": "/ediz-balkan/beraterfirma/berater/5931", "name": "Ediz Balkan"}, "current_club": {"href": "/crystal-palace/startseite/verein/873"}, "foot": "right", "joined": "Aug 2, 2018", "contract_expires": "Jun 30, 2022", "day_of_last_contract_extension": null, "outfitter": null, "social_media": ["http://twitter.com/PapiCheikhou", "http://www.instagram.com/roilionpapis8/"]}
{"type": "player", "href": "/nathan-ferguson/profil/spieler/507254", "parent": {"type": "club", "href": "/crystal-palace/startseite/verein/873/saison_id/2020", "seasoned_href": "https://www.transfermarkt.co.uk/crystal-palace/startseite/verein/873/saison_id/2020/saison_id/2021"}, "name_in_home_country": "Nathan Kirk-Patrick Ferguson", "date_of_birth": "Oct 6, 2000", "place_of_birth": {"country": "England", "city": "Birmingham"}, "age": "20", "height": "1,84 m", "citizienship": "England", "position": "Centre-Back", "player_agent": {"href": null, "name": null}, "current_club": {"href": "/crystal-palace/startseite/verein/873"}, "foot": "right", "joined": "Jul 27, 2020", "contract_expires": "Jun 30, 2023", "day_of_last_contract_extension": null, "outfitter": "Puma", "social_media": ["http://www.instagram.com/nath.ferguson/"]}
{"type": "player", "href": "/joachim-andersen/profil/spieler/260827", "parent": {"type": "club", "href": "/crystal-palace/startseite/verein/873/saison_id/2020", "seasoned_href": "https://www.transfermarkt.co.uk/crystal-palace/startseite/verein/873/saison_id/2020/saison_id/2021"}, "name_in_home_country": "Joachim Christian Andersen", "date_of_birth": "May 31, 1996", "place_of_birth": {"country": "Denmark", "city": "Frederiksberg"}, "age": "25", "height": "1,92 m", "citizienship": "Denmark", "position": "Centre-Back", "player_agent": {"href": "/icm-stellar-sports/beraterfirma/berater/190", "name": "ICM Stellar Sports"}, "current_club": {"href": "/crystal-palace/startseite/verein/873"}, "foot": "right", "joined": "Jul 28, 2021", "contract_expires": "Jun 30, 2026", "day_of_last_contract_extension": null, "outfitter": null, "social_media": ["http://www.facebook.com/Jokke5", "http://www.instagram.com/joachimandersen3/"]}
{"type": "player", "href": "/jordan-ayew/profil/spieler/108354", "parent": {"type": "club", "href": "/crystal-palace/startseite/verein/873/saison_id/2020", "seasoned_href": "https://www.transfermarkt.co.uk/crystal-palace/startseite/verein/873/saison_id/2020/saison_id/2021"}, "name_in_home_country": "Jordan Pierre Ayew", "date_of_birth": "Sep 11, 1991", "place_of_birth": {"country": "France", "city": "Marseille"}, "age": "30", "height": "1,82 m", "citizienship": "Ghana", "position": "Centre-Forward", "player_agent": {"href": "/wasserman/beraterfirma/berater/440", "name": "Wasserman"}, "current_club": {"href": "/crystal-palace/startseite/verein/873"}, "foot": "right", "joined": "Jul 25, 2019", "contract_expires": "Jun 30, 2022", "day_of_last_contract_extension": null, "outfitter": null, "social_media": ["http://twitter.com/jordan_ayew9", "http://www.instagram.com/jordanayew9/"]}
{"type": "player", "href": "/wilfried-zaha/profil/spieler/145988", "parent": {"type": "club", "href": "/crystal-palace/startseite/verein/873/saison_id/2020", "seasoned_href": "https://www.transfermarkt.co.uk/crystal-palace/startseite/verein/873/saison_id/2020/saison_id/2021"}, "name_in_home_country": "Dazet Wilfried Armel Zaha", "date_of_birth": "Nov 10, 1992", "place_of_birth": {"country": "Cote d'Ivoire", "city": "Abidjan"}, "age": "28", "height": "1,80 m", "citizienship": "Cote d'Ivoire", "position": "Left Winger", "player_agent": {"href": "/caa-base-ltd/beraterfirma/berater/674", "name": "CAA Base Ltd"}, "current_club": {"href": "/crystal-palace/startseite/verein/873"}, "foot": "right", "joined": "Feb 2, 2015", "contract_expires": "Jun 30, 2023", "day_of_last_contract_extension": "Aug 15, 2018", "outfitter": null, "social_media": ["http://twitter.com/wilfriedzaha", "http://www.facebook.com/Wilfriedzaha", "http://www.instagram.com/wilfriedzaha/"]}
{"type": "player", "href": "/tyrick-mitchell/profil/spieler/730893", "parent": {"type": "club", "href": "/crystal-palace/startseite/verein/873/saison_id/2020", "seasoned_href": "https://www.transfermarkt.co.uk/crystal-palace/startseite/verein/873/saison_id/2020/saison_id/2021"}, "name_in_home_country": null, "date_of_birth": "Sep 1, 1999", "place_of_birth": {"country": "England", "city": "London"}, "age": "22", "height": "1,75 m", "citizienship": "England", "position": "Left-Back", "player_agent": {"href": "/unique-sports-management/beraterfirma/berater/4142", "name": "Unique Sports Management"}, "current_club": {"href": "/crystal-palace/startseite/verein/873"}, "foot": "left", "joined": "Jul 1, 2020", "contract_expires": "Jun 30, 2025", "day_of_last_contract_extension": "Apr 13, 2021", "outfitter": null, "social_media": ["http://www.instagram.com/tmitch.27/"]}
{"type": "player", "href": "/james-tomkins/profil/spieler/61592", "parent": {"type": "club", "href": "/crystal-palace/startseite/verein/873/saison_id/2020", "seasoned_href": "https://www.transfermarkt.co.uk/crystal-palace/startseite/verein/873/saison_id/2020/saison_id/2021"}, "name_in_home_country": "James Oliver Charles Tomkins", "date_of_birth": "Mar 29, 1989", "place_of_birth": {"country": "England", "city": "Basildon"}, "age": "32", "height": "1,92 m", "citizienship": "England", "position": "Centre-Back", "player_agent": {"href": null, "name": null}, "current_club": {"href": "/crystal-palace/startseite/verein/873"}, "foot": "right", "joined": "Jul 5, 2016", "contract_expires": "Jun 30, 2022", "day_of_last_contract_extension": "Oct 17, 2019", "outfitter": "adidas", "social_media": ["http://twitter.com/TomkinsOfficial", "http://www.instagram.com/TomkinsOfficial/"]}
{"type": "player", "href": "/jack-butland/profil/spieler/128899", "parent": {"type": "club", "href": "/crystal-palace/startseite/verein/873/saison_id/2020", "seasoned_href": "https://www.transfermarkt.co.uk/crystal-palace/startseite/verein/873/saison_id/2020/saison_id/2021"}, "name_in_home_country": null, "date_of_birth": "Mar 10, 1993", "place_of_birth": {"country": "England", "city": "Bristol"}, "age": "28", "height": "1,96 m", "citizienship": "England", "position": "Goalkeeper", "player_agent": {"href": "/triple-s-sports-and-entertainment-group-ltd/beraterfirma/berater/4216", "name": "Triple S Sports"}, "current_club": {"href": "/crystal-palace/startseite/verein/873"}, "foot": "right", "joined": "Oct 16, 2020", "contract_expires": "Jun 30, 2023", "day_of_last_contract_extension": null, "outfitter": "Nike", "social_media": ["http://twitter.com/JackButland_One", "http://www.instagram.com/jbutland_/", "http://officialjackbutland.com"]}
{"type": "player", "href": "/jeffrey-schlupp/profil/spieler/157506", "parent": {"type": "club", "href": "/crystal-palace/startseite/verein/873/saison_id/2020", "seasoned_href": "https://www.transfermarkt.co.uk/crystal-palace/startseite/verein/873/saison_id/2020/saison_id/2021"}, "name_in_home_country": null, "date_of_birth": "Dec 23, 1992", "place_of_birth": {"country": "Germany", "city": "Hamburg"}, "age": "28", "height": "1,78 m", "citizienship": "Ghana", "position": "Left Midfield", "player_agent": {"href": "/unique-sports-management/beraterfirma/berater/4142", "name": "Unique Sports Management"}, "current_club": {"href": "/crystal-palace/startseite/verein/873"}, "foot": "left", "joined": "Jan 13, 2017", "contract_expires": "Jun 30, 2022", "day_of_last_contract_extension": null, "outfitter": "adidas", "social_media": ["http://twitter.com/Jeffrey_Schlupp", "http://www.instagram.com/jeffreyschlupp/"]}
{"type": "player", "href": "/will-hughes/profil/spieler/207014", "parent": {"type": "club", "href": "/crystal-palace/startseite/verein/873/saison_id/2020", "seasoned_href": "https://www.transfermarkt.co.uk/crystal-palace/startseite/verein/873/saison_id/2020/saison_id/2021"}, "name_in_home_country": "William James Hughes", "date_of_birth": "Apr 17, 1995", "place_of_birth": {"country": "England", "city": "Weybridge"}, "age": "26", "height": "1,85 m", "citizienship": "England", "position": "Central Midfield", "player_agent": {"href": "/two-touch-agency/beraterfirma/berater/7069", "name": "Two Touch Agency"}, "current_club": {"href": "/crystal-palace/startseite/verein/873"}, "foot": "left", "joined": "Aug 28, 2021", "contract_expires": "Jun 30, 2024", "day_of_last_contract_extension": null, "outfitter": "Nike", "social_media": ["http://twitter.com/wjhughes19"]}
{"type": "player", "href": "/vicente-guaita/profil/spieler/64399", "parent": {"type": "club", "href": "/crystal-palace/startseite/verein/873/saison_id/2020", "seasoned_href": "https://www.transfermarkt.co.uk/crystal-palace/startseite/verein/873/saison_id/2020/saison_id/2021"}, "name_in_home_country": "Vicente Guaita Panadero", "date_of_birth": "Jan 10, 1987", "place_of_birth": {"country": "Spain", "city": "Torrente"}, "age": "34", "height": "1,90 m", "citizienship": "Spain", "position": "Goalkeeper", "player_agent": {"href": "/jcrsport-goalkeeper/beraterfirma/berater/5570", "name": "JCRsport"}, "current_club": {"href": "/crystal-palace/startseite/verein/873"}, "foot": "right", "joined": "Jul 1, 2018", "contract_expires": "Jun 30, 2023", "day_of_last_contract_extension": "Feb 1, 2021", "outfitter": "Sells", "social_media": ["http://twitter.com/vguaita13", "http://www.instagram.com/vguaita_13/"]}
{"type": "player", "href": "/michael-olise/profil/spieler/566723", "parent": {"type": "club", "href": "/crystal-palace/startseite/verein/873/saison_id/2020", "seasoned_href": "https://www.transfermarkt.co.uk/crystal-palace/startseite/verein/873/saison_id/2020/saison_id/2021"}, "name_in_home_country": "Michael Akpovie Olise", "date_of_birth": "Dec 12, 2001", "place_of_birth": {"country": "England", "city": "London"}, "age": "19", "height": "1,84 m", "citizienship": "France", "position": "Attacking Midfield", "player_agent": {"href": null, "name": null}, "current_club": {"href": "/crystal-palace/startseite/verein/873"}, "foot": "left", "joined": "Jul 8, 2021", "contract_expires": "Jun 30, 2026", "day_of_last_contract_extension": null, "outfitter": "Nike", "social_media": ["http://www.instagram.com/m.olise/"]}
{"type": "player", "href": "/jean-philippe-mateta/profil/spieler/420002", "parent": {"type": "club", "href": "/crystal-palace/startseite/verein/873/saison_id/2020", "seasoned_href": "https://www.transfermarkt.co.uk/crystal-palace/startseite/verein/873/saison_id/2020/saison_id/2021"}, "name_in_home_country": null, "date_of_birth": "Jun 28, 1997", "place_of_birth": {"country": "France", "city": "Sevran"}, "age": "24", "height": "1,92 m", "citizienship": "France", "position": "Centre-Forward", "player_agent": {"href": "/paul-latouche/beraterfirma/berater/8216", "name": "Paul Latouche"}, "current_club": {"href": "/crystal-palace/startseite/verein/873"}, "foot": "right", "joined": "Jan 21, 2021", "contract_expires": "Jun 30, 2022", "day_of_last_contract_extension": null, "outfitter": null, "social_media": ["http://www.instagram.com/iammateta/"]}
{"type": "player", "href": "/christian-benteke/profil/spieler/50201", "parent": {"type": "club", "href": "/crystal-palace/startseite/verein/873/saison_id/2020", "seasoned_href": "https://www.transfermarkt.co.uk/crystal-palace/startseite/verein/873/saison_id/2020/saison_id/2021"}, "name_in_home_country": "Christian Benteke Liolo", "date_of_birth": "Dec 3, 1990", "place_of_birth": {"country": "Zaire", "city": "Kinshasa"}, "age": "30", "height": "1,90 m", "citizienship": "Belgium", "position": "Centre-Forward", "player_agent": {"href": "/mla-management/beraterfirma/berater/1267", "name": "MLA Management"}, "current_club": {"href": "/crystal-palace/startseite/verein/873"}, "foot": "right", "joined": "Aug 20, 2016", "contract_expires": "Jun 30, 2023", "day_of_last_contract_extension": "Jun 3, 2021", "outfitter": "Nike", "social_media": ["http://twitter.com/bentekechris20", "http://www.facebook.com/BentekeOfficial?fref=ts", "http://www.instagram.com/christianbenteke/"]}
{"type": "player", "href": "/nathaniel-clyne/profil/spieler/85177", "parent": {"type": "club", "href": "/crystal-palace/startseite/verein/873/saison_id/2020", "seasoned_href": "https://www.transfermarkt.co.uk/crystal-palace/startseite/verein/873/saison_id/2020/saison_id/2021"}, "name_in_home_country": "Nathaniel Edwin Clyne", "date_of_birth": "Apr 5, 1991", "place_of_birth": {"country": "England", "city": "London"}, "age": "30", "height": "1,75 m", "citizienship": "England", "position": "Right-Back", "player_agent": {"href": null, "name": null}, "current_club": {"href": "/crystal-palace/startseite/verein/873"}, "foot": "right", "joined": "Oct 14, 2020", "contract_expires": "Jun 30, 2022", "day_of_last_contract_extension": "Jan 25, 2021", "outfitter": null, "social_media": ["http://twitter.com/Nathaniel_Clyne", "http://www.facebook.com/nathanielclyne2/?fref=ts", "http://www.instagram.com/nathaniel_clyne/"]}
